amsdal_crm/Third-Party Materials - AMSDAL Dependencies - License Notices.md
amsdal_crm/__about__.py
amsdal_crm/__init__.py
amsdal_crm/app.py
amsdal_crm/constants.py
amsdal_crm/errors.py
amsdal_crm/settings.py
amsdal_crm/fixtures/__init__.py
amsdal_crm/fixtures/permissions.py
amsdal_crm/fixtures/pipelines.py
amsdal_crm/lifecycle/__init__.py
amsdal_crm/lifecycle/consumer.py
amsdal_crm/migrations/0000_initial.py
amsdal_crm/models/__init__.py
amsdal_crm/models/activity.py
amsdal_crm/models/attachment.py
amsdal_crm/models/custom_field_definition.py
amsdal_crm/models/deal.py
amsdal_crm/models/entity.py
amsdal_crm/models/pipeline.py
amsdal_crm/models/stage.py
amsdal_crm/models/workflow_rule.py
amsdal_crm/services/__init__.py
amsdal_crm/services/activity_service.py
amsdal_crm/services/custom_field_service.py
amsdal_crm/services/deal_service.py
amsdal_crm/services/email_service.py
amsdal_crm/services/workflow_service.py
amsdal_crm-0.2.0.dist-info/METADATA
amsdal_crm-0.2.0.dist-info/WHEEL
amsdal_crm-0.2.0.dist-info/RECORD
