Metadata-Version: 2.4
Name: amsdal_crm
Version: 0.2.0
Summary: amsdal-crm plugin for AMSDAL Framework
Requires-Python: >=3.11
Requires-Dist: aiohttp==3.12.15
Requires-Dist: amsdal-cli>=0.5.7
Requires-Dist: amsdal-data>=0.5.9
Requires-Dist: amsdal-models>=0.5.9
Requires-Dist: amsdal-utils>=0.5.4
Requires-Dist: amsdal>=0.5.6
Requires-Dist: mcp>=0.1
Requires-Dist: openai==1.100.2
Requires-Dist: pydantic-settings~=2.12
Requires-Dist: pydantic~=2.12
Requires-Dist: pymupdf>=1.24.10
